ml_commons/__init__.py
ml_commons/ax.py
ml_commons/pytorch/__init__.py
ml_commons/pytorch/image_pool.py
ml_commons/pytorch/util.py
ml_commons/pytorch/datasets/__init__.py
ml_commons/pytorch/datasets/image_folder.py
ml_commons/pytorch/datasets/unaligned.py
ml_commons/pytorch/losses/__init__.py
ml_commons/pytorch/losses/focal.py
ml_commons/pytorch/losses/gan.py
ml_commons/pytorch/losses/ntxent.py
ml_commons/pytorch/losses/online_triplet.py
ml_commons/pytorch/models/__init__.py
ml_commons/pytorch/models/checkpointed.py
ml_commons/pytorch/models/cpc.py
ml_commons/pytorch/models/cyclegan.py
ml_commons/pytorch/models/diffpool.py
ml_commons/pytorch/models/efficientnet.py
ml_commons/pytorch/models/gcn.py
ml_commons/pytorch/models/graph.py
ml_commons/pytorch/models/graphconv.py
ml_commons/pytorch/models/inception.py
ml_commons/pytorch/models/itq.py
ml_commons/pytorch/models/mlp.py
ml_commons/pytorch/models/pixelcnn.py
ml_commons/pytorch/models/positional_encoding.py
ml_commons/pytorch/models/resnet.py
ml_commons/pytorch/models/simclr.py
ml_commons/pytorch/models/stitch.py
ml_commons/pytorch/models/vqvae2.py
ml_commons/pytorch/transforms/__init__.py
ml_commons/pytorch/transforms/graph.py
ml_commons/util/__init__.py
ml_commons/util/logger.py
ml_commons/util/metrics.py
ml_commons/util/path.py
ml_commons/util/sampling.py
ml_commons/util/stdout_capturing.py
ml_commons/util/timer.py
tests/__init__.py
tests/test_automain.py
tests/test_module.py
ml_commons-2.3.0.dist-info/METADATA
ml_commons-2.3.0.dist-info/WHEEL
ml_commons-2.3.0.dist-info/top_level.txt
ml_commons-2.3.0.dist-info/RECORD
