Metadata-Version: 2.1
Name: ml-commons
Version: 2.3.0
Summary: UNKNOWN
Home-page: UNKNOWN
Author: Yigit Ozen
Author-email: UNKNOWN
License: UNKNOWN
Platform: UNKNOWN
Requires-Dist: numpy
Requires-Dist: tqdm
